sivuvahti/__init__.py
sivuvahti/nakyma.py
sivuvahti/sivuvahti.py
sivuvahti/static/sivuvahti/js/sivuvahti.js
django_sivuvahti-0.4.1.dist-info/METADATA
django_sivuvahti-0.4.1.dist-info/WHEEL
django_sivuvahti-0.4.1.dist-info/entry_points.txt
django_sivuvahti-0.4.1.dist-info/historia.json
django_sivuvahti-0.4.1.dist-info/top_level.txt
django_sivuvahti-0.4.1.dist-info/RECORD
