Metadata-Version: 2.4
Name: django-sivuvahti
Version: 0.4.1
Summary: Django-laajennos avoinna olevien sivujen seuraamiseen
Author-email: Antti Hautaniemi <antti.hautaniemi@me.com>
License: MIT
Project-URL: Repository, https://github.com/an7oine/django-sivuvahti.git
Requires-Python: >=3.8
Requires-Dist: celery-viestikanava>=0.2
Requires-Dist: django-pistoke>=0.9
Requires-Dist: django-sivumedia
